addext/__init__.py
addext/addext.py
addext/pronom_xml_to_json.py
addext-2.0.1.data/scripts/addext.py
addext-2.0.1.dist-info/LICENSE
addext-2.0.1.dist-info/METADATA
addext-2.0.1.dist-info/WHEEL
addext-2.0.1.dist-info/top_level.txt
addext-2.0.1.dist-info/RECORD
